bone/__init__.py
bone-0.1.1.dist-info/LICENSE
bone-0.1.1.dist-info/METADATA
bone-0.1.1.dist-info/WHEEL
bone-0.1.1.dist-info/top_level.txt
bone-0.1.1.dist-info/RECORD
