Metadata-Version: 2.1
Name: bone
Version: 0.1.1
Summary: The simple Python web framework
Home-page: http://github.com/qe/bone
Author: Alex Ismodes
Author-email: helloemailmerighthere@gmail.com
License: MIT
Keywords: bone web framework webframework
Platform: UNKNOWN
Classifier: Development Status :: 1 - Planning
Classifier: Environment :: Web Environment
Classifier: Intended Audience :: Developers
Classifier: License :: OSI Approved :: MIT License
Classifier: Programming Language :: Python
Classifier: Topic :: Internet :: WWW/HTTP
Classifier: Topic :: Internet :: WWW/HTTP :: Dynamic Content
Classifier: Topic :: Internet :: WWW/HTTP :: WSGI
Classifier: Topic :: Software Development :: Libraries :: Application Frameworks
Classifier: Topic :: Software Development :: Libraries :: Python Modules
License-File: LICENSE
